{"spider": "DB0118", "allowed_domains": ["worldscientific.com"], "start_urls": ["https://www.worldscientific.com/action/showPublications"], "website": "worldscientific", "away": "get", "settings": {"LOG_FILE": "./Hive/LOG/DB0118.log", "FILES_STORE": "/home/ac/桌面/Hive/Hive/Honey_CSV/FILE/"}, "item": {"class": "DB0118", "loader": "NewItemLoader", "attrs": {"title": [{"method": "xpath", "args": ["//h1/text()"]}], "abstract": [{"method": "xpath", "args": ["//div[@class='NLM_abstract']//p/text()"]}]}}}